vacancy_resume_backend/main.py
vacancy_resume_backend-0.1.6.dist-info/entry_points.txt
vacancy_resume_backend-0.1.6.dist-info/METADATA
vacancy_resume_backend-0.1.6.dist-info/WHEEL
vacancy_resume_backend-0.1.6.dist-info/RECORD
