Metadata-Version: 2.1
Name: vacancy-resume-backend
Version: 0.1.6
Summary: 
Author: Alexander
Author-email: cahr2001@mail.ru
Requires-Python: >=3.8.1,<4.0.0
Classifier: Programming Language :: Python :: 3
Classifier: Programming Language :: Python :: 3.9
Classifier: Programming Language :: Python :: 3.10
Classifier: Programming Language :: Python :: 3.11
Requires-Dist: fastapi (>=0.104.0,<0.105.0)
Requires-Dist: langchain (>=0.0.325,<0.0.326)
Requires-Dist: pgvector (>=0.2.3,<0.3.0)
Requires-Dist: psycopg2-binary (>=2.9.9,<3.0.0)
Requires-Dist: python-multipart (>=0.0.6,<0.0.7)
Requires-Dist: tiktoken (>=0.5.1,<0.6.0)
Requires-Dist: uvicorn (>=0.23.2,<0.24.0)
